otrs/__init__.py
otrs/client.py
otrs/objects.py
otrs/faq/__init__.py
otrs/faq/objects.py
otrs/faq/operations.py
otrs/faq/template.py
otrs/session/__init__.py
otrs/session/operations.py
otrs/ticket/__init__.py
otrs/ticket/objects.py
otrs/ticket/operations.py
otrs/ticket/template.py
python_otrs-0.4.3.dist-info/DESCRIPTION.rst
python_otrs-0.4.3.dist-info/METADATA
python_otrs-0.4.3.dist-info/RECORD
python_otrs-0.4.3.dist-info/WHEEL
python_otrs-0.4.3.dist-info/metadata.json
python_otrs-0.4.3.dist-info/top_level.txt
