Metadata-Version: 2.0
Name: python-otrs
Version: 0.4.3
Summary: A programmatic interface to OTRS SOAP API.
Home-page: https://github.com/ewsterrenburg/python-otrs
Author: Erwin Sterrenburg
Author-email: e.w.sterrenburg@gmail.com
License: GPLv3
Keywords: otrs ticket support soap interface helpdesk
Platform: UNKNOWN
Classifier: Development Status :: 4 - Beta
Classifier: Environment :: Web Environment
Classifier: Natural Language :: English
Classifier: Intended Audience :: Developers
Classifier: Operating System :: OS Independent
Classifier: Topic :: Office/Business
Classifier: Topic :: Software Development :: Bug Tracking
Classifier: License :: OSI Approved :: GNU General Public License v3 (GPLv3)
Classifier: Programming Language :: Python :: 2
Classifier: Programming Language :: Python :: 2.7
Classifier: Programming Language :: Python :: 3
Classifier: Programming Language :: Python :: 3.5
Requires-Python: >=2.7, !=3.0.*, !=3.1.*, !=3.2.*, !=3.3.*, !=3.4.*, <4
Requires-Dist: defusedxml
